cas/__init__.py
cas/apps.py
cas/backends.py
cas/decorators.py
cas/exceptions.py
cas/middleware.py
cas/models.py
cas/utils.py
cas/views.py
cas/tests/__init__.py
cas/tests/factories.py
cas/tests/test_backend.py
cas/tests/test_smoke.py
cas/tests/test_views.py
django_cas_client-1.5.3.dist-info/AUTHORS
django_cas_client-1.5.3.dist-info/LICENSE.mit
django_cas_client-1.5.3.dist-info/METADATA
django_cas_client-1.5.3.dist-info/WHEEL
django_cas_client-1.5.3.dist-info/top_level.txt
django_cas_client-1.5.3.dist-info/zip-safe
django_cas_client-1.5.3.dist-info/RECORD
