Metadata-Version: 2.1
Name: django-cas-client
Version: 1.5.3
Summary: Django Cas Client
Home-page: http://github.com/kstateome/django-cas/
Author: Derek Stegelman, Garrett Pennington
Author-email: derekst@k-state.edu, garrettp@gmail.com
License: MIT
Keywords: django cas
Platform: UNKNOWN
Classifier: Development Status :: 5 - Production/Stable
Classifier: Environment :: Web Environment
Classifier: Framework :: Django
Classifier: Framework :: Django :: 1.5
Classifier: Framework :: Django :: 1.6
Classifier: Framework :: Django :: 1.7
Classifier: Intended Audience :: Developers
Classifier: Natural Language :: English
Classifier: Operating System :: OS Independent
Classifier: Programming Language :: Python
Classifier: Programming Language :: Python :: 3
Classifier: Programming Language :: Python :: 2
Classifier: Topic :: Internet :: WWW/HTTP :: Dynamic Content :: CGI Tools/Libraries
Classifier: Topic :: Utilities
Classifier: License :: OSI Approved :: MIT License
